merge_cobertura/__init__.py
merge_cobertura/coverage_source.py
merge_cobertura/coverage_stats.py
merge_cobertura/main.py
merge_cobertura-0.0.1.dist-info/LICENSE
merge_cobertura-0.0.1.dist-info/METADATA
merge_cobertura-0.0.1.dist-info/WHEEL
merge_cobertura-0.0.1.dist-info/entry_points.txt
merge_cobertura-0.0.1.dist-info/top_level.txt
merge_cobertura-0.0.1.dist-info/RECORD
