Metadata-Version: 2.1
Name: merge_cobertura
Version: 0.0.1
Summary: A CLI tool to merge multiple coverage report in cobertura XML format.
Author-email: Louis DEVIE <louisdevie.contact@gmail.com>
Project-URL: Homepage, https://github.com/louisdevie/merge-cobertura
Project-URL: Issues, https://github.com/louisdevie/merge-cobertura/issues
Classifier: Programming Language :: Python :: 3
Classifier: License :: OSI Approved :: MIT License
Classifier: Operating System :: OS Independent
Requires-Python: >=3.8
License-File: LICENSE
Requires-Dist: bs4
Requires-Dist: lxml
